calendarutil/__init__.py
calendarutil/quarter.py
calendarutil/month/__init__.py
calendarutil/month/from_range.py
calendarutil/month/from_year.py
calendarutil/month/util.py
tests/__init__.py
tests/test_calendar_util_pytest.py
tests/test_calendar_util_unittest.py
calendarutil-2021.4.1.dist-info/LICENSE
calendarutil-2021.4.1.dist-info/METADATA
calendarutil-2021.4.1.dist-info/WHEEL
calendarutil-2021.4.1.dist-info/top_level.txt
calendarutil-2021.4.1.dist-info/RECORD
