Metadata-Version: 2.1
Name: calendarutil
Version: 2021.4.1
Summary: Simple and lightweight calendar support for python datetime.date
Home-page: https://github.com/github-suraj/calendar-util
Author: Suraj Jaiswal
Author-email: surajkumarjaiswal053@gmail.com
License: UNKNOWN
Project-URL: Detail Usage, https://github.com/github-suraj/calendar-util/blob/main/README.md
Platform: UNKNOWN
